MANIFEST.in
README.rst
dlmap
setup.py
mob_map_dl/__init__.py
mob_map_dl/common.py
mob_map_dl/download.py
mob_map_dl/install.py
mob_map_dl/local.py
mob_map_dl/main.py
mobile_map_downloader.egg-info/PKG-INFO
mobile_map_downloader.egg-info/SOURCES.txt
mobile_map_downloader.egg-info/dependency_links.txt
mobile_map_downloader.egg-info/requires.txt
mobile_map_downloader.egg-info/top_level.txt
test/test_common.py
test/test_download.py
test/test_install.py
test/test_local.py
test/test_main.py