Metadata-Version: 1.1
Name: mobile-map-downloader
Version: 0.1.10
Summary: Download maps for mobile devices over broadband, with a personal computer.
Home-page: https://github.com/eike-welk/mobile_map_downloader
Author: Eike Welk
Author-email: eike.welk@gmx.net
License: GNU General Public License v3 (GPLv3)
Keywords: map,GPS,mobile device,download
Platform: UNKNOWN
Classifier: Development Status :: 4 - Beta
Classifier: Topic :: Internet :: WWW/HTTP
Classifier: Topic :: Utilities
Classifier: Environment :: Console
Classifier: Intended Audience :: End Users/Desktop
Classifier: Operating System :: POSIX
Classifier: Programming Language :: Python :: 2.7
Classifier: License :: OSI Approved :: GNU General Public License v3 (GPLv3)
